git_ai_summarize/__init__.py
git_ai_summarize/models.py
git_ai_summarize/summarize.py
git_ai_summarize/utils.py
git_ai_summarize-0.1.4.dist-info/LICENSE
git_ai_summarize-0.1.4.dist-info/METADATA
git_ai_summarize-0.1.4.dist-info/WHEEL
git_ai_summarize-0.1.4.dist-info/entry_points.txt
git_ai_summarize-0.1.4.dist-info/top_level.txt
git_ai_summarize-0.1.4.dist-info/RECORD
