Metadata-Version: 2.1
Name: git-ai-summarize
Version: 0.1.4
Summary: AI-powered git commands for summarizing changes
Author-email: Kevin Beaulieu <opensource@kevinmbeaulieu.com>
Project-URL: Homepage, https://github.com/kevinmbeaulieu/git-ai-summarize
Project-URL: Issues, https://github.com/kevinmbeaulieu/git-ai-summarize/issues
Classifier: Programming Language :: Python :: 3
Classifier: License :: OSI Approved :: GNU General Public License v3 (GPLv3)
Classifier: Operating System :: OS Independent
Requires-Python: >=3.8
License-File: LICENSE
Requires-Dist: langchain-core
Requires-Dist: langchain-anthropic
Requires-Dist: langchain-openai
Requires-Dist: langchain-google-genai
Requires-Dist: langchain-mistralai
Requires-Dist: langchain-fireworks
Requires-Dist: langchain-together
Requires-Dist: langchain-google-vertexai
Requires-Dist: langchain-groq
Requires-Dist: langchain-nvidia-ai-endpoints
Requires-Dist: langchain-ollama
Requires-Dist: langchain-ai21
Requires-Dist: langchain-upstage
Requires-Dist: langchain-databricks
Requires-Dist: langchain-ibm
Requires-Dist: langchain-xai
